excel_normalizer/__init__.py
excel_normalizer/cli.py
excel_normalizer-0.3.dist-info/LICENSE
excel_normalizer-0.3.dist-info/METADATA
excel_normalizer-0.3.dist-info/WHEEL
excel_normalizer-0.3.dist-info/entry_points.txt
excel_normalizer-0.3.dist-info/top_level.txt
excel_normalizer-0.3.dist-info/RECORD
