Metadata-Version: 2.1
Name: excel_normalizer
Version: 0.3
Classifier: Programming Language :: Python :: 3
Classifier: License :: OSI Approved :: MIT License
Classifier: Operating System :: OS Independent
Requires-Python: >=3.6
License-File: LICENSE
Requires-Dist: pandas
Requires-Dist: pyarrow
Requires-Dist: openpyxl
